fastapi_db/__init__.py
fastapi_db/constants.py
fastapi_db/exceptions.py
fastapi_db/extensions.py
fastapi_db/middleware.py
fastapi_db/models.py
fastapi_db/snowflake.py
fastapi_db/transaction_enums.py
fastapi_db/types.py
fastapi_db/utils.py
fastapi_db-0.7.8.dist-info/LICENSE
fastapi_db-0.7.8.dist-info/METADATA
fastapi_db-0.7.8.dist-info/WHEEL
fastapi_db-0.7.8.dist-info/top_level.txt
fastapi_db-0.7.8.dist-info/RECORD
