Metadata-Version: 2.1
Name: fastapi_db
Version: 0.7.8
Summary: fastapi使用sqlalchemy任意接口位置获取db上下文，非常安全并可靠。
Home-page: https://github.com/breezechime/fastapi_db
Author: 且听风铃、我是指针*、ZDLAY、KYZ
Author-email: breezechime@163.com
License: MIT
Keywords: fastapi,db,sqlalchemy
Classifier: License :: OSI Approved :: MIT License
Classifier: Operating System :: OS Independent
Classifier: Programming Language :: Python :: 3
Requires-Python: >=3.6
License-File: LICENSE
Requires-Dist: sqlalchemy >=1.4.46
Requires-Dist: fastapi
